e2e_sae/__init__.py
e2e_sae/data.py
e2e_sae/hooks.py
e2e_sae/loader.py
e2e_sae/log.py
e2e_sae/losses.py
e2e_sae/metrics.py
e2e_sae/plotting.py
e2e_sae/settings.py
e2e_sae/types.py
e2e_sae/utils.py
e2e_sae/models/__init__.py
e2e_sae/models/mlp.py
e2e_sae/models/sparsifiers.py
e2e_sae/models/transformers.py
e2e_sae/scripts/__init__.py
e2e_sae/scripts/upload_hf_dataset.py
e2e_sae-2.1.1.dist-info/LICENSE
e2e_sae-2.1.1.dist-info/METADATA
e2e_sae-2.1.1.dist-info/WHEEL
e2e_sae-2.1.1.dist-info/top_level.txt
e2e_sae-2.1.1.dist-info/RECORD
