Metadata-Version: 2.1
Name: e2e_sae
Version: 2.1.1
Summary: Repo for training sparse autoencoders end-to-end
Project-URL: repository, https://github.com/ApolloResearch/e2e_sae
Requires-Python: >=3.11
License-File: LICENSE
Requires-Dist: torch
Requires-Dist: torchvision
Requires-Dist: einops
Requires-Dist: pydantic
Requires-Dist: wandb
Requires-Dist: fire
Requires-Dist: tqdm
Requires-Dist: pytest
Requires-Dist: ipykernel
Requires-Dist: transformer-lens
Requires-Dist: jaxtyping
Requires-Dist: python-dotenv
Requires-Dist: zstandard
Requires-Dist: matplotlib
Requires-Dist: seaborn
Requires-Dist: umap-learn
Requires-Dist: tenacity
Requires-Dist: statsmodels
Requires-Dist: automated-interpretability
Provides-Extra: dev
Requires-Dist: ruff ; extra == 'dev'
Requires-Dist: pyright ; extra == 'dev'
Requires-Dist: pre-commit ; extra == 'dev'
